Basi_CLI/__init__.py
Basi_CLI/cli.py
Basi_CLI-1.7.dist-info/METADATA
Basi_CLI-1.7.dist-info/WHEEL
Basi_CLI-1.7.dist-info/entry_points.txt
Basi_CLI-1.7.dist-info/top_level.txt
Basi_CLI-1.7.dist-info/RECORD
