Metadata-Version: 2.1
Name: Basi-CLI
Version: 1.7
Summary: UNKNOWN
Home-page: UNKNOWN
Author: Lakshman Raaj Senthil Nathan
Author-email: lakshmanraajs@gmail.com
License: UNKNOWN
Platform: UNKNOWN
Classifier: Programming Language :: Python :: 3
Classifier: License :: OSI Approved :: MIT License
Classifier: Operating System :: OS Independent
Requires-Dist: click
Requires-Dist: numpy
Requires-Dist: pandas
Requires-Dist: requests
Requires-Dist: typer
